{
  "name": "overhauledstructures:overhauleddungeonprison/ovdp_prison_3x5",
  "fallback": "minecraft:empty",
  "elements": [
    {
      "weight": 5,
      "element": {
        "location": "overhauledstructures:ovdp/ovdp_prison_3x5_1",
        "processors": "minecraft:empty",
        "projection": "rigid",
        "element_type": "minecraft:single_pool_element"
      }
    },
    {
      "weight": 5,
      "element": {
        "location": "overhauledstructures:ovdp/ovdp_prison_3x5_2",
        "processors": "minecraft:empty",
        "projection": "rigid",
        "element_type": "minecraft:single_pool_element"
      }
    },
    {
      "weight": 5,
      "element": {
        "location": "overhauledstructures:ovdp/ovdp_prison_3x5_3",
        "processors": "minecraft:empty",
        "projection": "rigid",
        "element_type": "minecraft:single_pool_element"
      }
    },
    {
      "weight": 5,
      "element": {
        "location": "overhauledstructures:ovdp/ovdp_prison_3x5_4",
        "processors": "minecraft:empty",
        "projection": "rigid",
        "element_type": "minecraft:single_pool_element"
      }
    },
    {
      "weight": 5,
      "element": {
        "location": "overhauledstructures:ovdp/ovdp_prison_3x5_5",
        "processors": "minecraft:empty",
        "projection": "rigid",
        "element_type": "minecraft:single_pool_element"
      }
    },
    {
      "weight": 5,
      "element": {
        "location": "overhauledstructures:ovdp/ovdp_prison_3x5_6",
        "processors": "minecraft:empty",
        "projection": "rigid",
        "element_type": "minecraft:single_pool_element"
      }
    },
    {
      "weight": 5,
      "element": {
        "location": "overhauledstructures:ovdp/ovdp_prison_3x5_7",
        "processors": "minecraft:empty",
        "projection": "rigid",
        "element_type": "minecraft:single_pool_element"
      }
    },
    {
      "weight": 5,
      "element": {
        "location": "overhauledstructures:ovdp/ovdp_prison_3x5_8",
        "processors": "minecraft:empty",
        "projection": "rigid",
        "element_type": "minecraft:single_pool_element"
      }
    },
    {
      "weight": 5,
      "element": {
        "location": "overhauledstructures:ovdp/ovdp_prison_3x5_9",
        "processors": "minecraft:empty",
        "projection": "rigid",
        "element_type": "minecraft:single_pool_element"
      }
    },
    {
      "weight": 5,
      "element": {
        "location": "overhauledstructures:ovdp/ovdp_prison_3x5_10",
        "processors": "minecraft:empty",
        "projection": "rigid",
        "element_type": "minecraft:single_pool_element"
      }
    },
    {
      "weight": 5,
      "element": {
        "location": "overhauledstructures:ovdp/ovdp_prison_3x5_11",
        "processors": "minecraft:empty",
        "projection": "rigid",
        "element_type": "minecraft:single_pool_element"
      }
    },
    {
      "weight": 5,
      "element": {
        "location": "overhauledstructures:ovdp/ovdp_prison_3x5_12",
        "processors": "minecraft:empty",
        "projection": "rigid",
        "element_type": "minecraft:single_pool_element"
      }
    },
    {
      "weight": 5,
      "element": {
        "location": "overhauledstructures:ovdp/ovdp_prison_3x5_13",
        "processors": "minecraft:empty",
        "projection": "rigid",
        "element_type": "minecraft:single_pool_element"
      }
    },
    {
      "weight": 5,
      "element": {
        "location": "overhauledstructures:ovdp/ovdp_prison_3x5_14",
        "processors": "minecraft:empty",
        "projection": "rigid",
        "element_type": "minecraft:single_pool_element"
      }
    },
    {
      "weight": 5,
      "element": {
        "location": "overhauledstructures:ovdp/ovdp_prison_3x5_15",
        "processors": "minecraft:empty",
        "projection": "rigid",
        "element_type": "minecraft:single_pool_element"
      }
    },
    {
      "weight": 5,
      "element": {
        "location": "overhauledstructures:ovdp/ovdp_prison_3x5_16",
        "processors": "minecraft:empty",
        "projection": "rigid",
        "element_type": "minecraft:single_pool_element"
      }
    },
    {
      "weight": 5,
      "element": {
        "location": "overhauledstructures:ovdp/ovdp_prison_3x5_17",
        "processors": "minecraft:empty",
        "projection": "rigid",
        "element_type": "minecraft:single_pool_element"
      }
    },
    {
      "weight": 5,
      "element": {
        "location": "overhauledstructures:ovdp/ovdp_prison_3x5_18",
        "processors": "minecraft:empty",
        "projection": "rigid",
        "element_type": "minecraft:single_pool_element"
      }
    },
    {
      "weight": 5,
      "element": {
        "location": "overhauledstructures:ovdp/ovdp_prison_3x5_19",
        "processors": "minecraft:empty",
        "projection": "rigid",
        "element_type": "minecraft:single_pool_element"
      }
    },
    {
      "weight": 5,
      "element": {
        "location": "overhauledstructures:ovdp/ovdp_prison_3x5_20",
        "processors": "minecraft:empty",
        "projection": "rigid",
        "element_type": "minecraft:single_pool_element"
      }
    }
  ]
}