{
  "name": "overhauledstructures:overhauleddungeonspiders/ovds_room_part_hanging",
  "fallback": "overhauledstructures:overhauleddungeonspiders/ovds_room_part_hanging",
  "elements": [
    {
      "weight": 5,
      "element": {
        "location": "overhauledstructures:ovds/ovds_room_part_hanging_1",
        "processors": "minecraft:empty",
        "projection": "rigid",
        "element_type": "minecraft:single_pool_element"
      }
    },
    {
      "weight": 5,
      "element": {
        "location": "overhauledstructures:ovds/ovds_room_part_hanging_2",
        "processors": "minecraft:empty",
        "projection": "rigid",
        "element_type": "minecraft:single_pool_element"
      }
    },
    {
      "weight": 5,
      "element": {
        "location": "overhauledstructures:ovds/ovds_room_part_hanging_3",
        "processors": "minecraft:empty",
        "projection": "rigid",
        "element_type": "minecraft:single_pool_element"
      }
    },
    {
      "weight": 5,
      "element": {
        "location": "overhauledstructures:ovds/ovds_room_part_hanging_4",
        "processors": "minecraft:empty",
        "projection": "rigid",
        "element_type": "minecraft:single_pool_element"
      }
    },
    {
      "weight": 5,
      "element": {
        "location": "overhauledstructures:ovds/ovds_room_part_hanging_5",
        "processors": "minecraft:empty",
        "projection": "rigid",
        "element_type": "minecraft:single_pool_element"
      }
    },
    {
      "weight": 5,
      "element": {
        "location": "overhauledstructures:ovds/ovds_room_part_hanging_6",
        "processors": "minecraft:empty",
        "projection": "rigid",
        "element_type": "minecraft:single_pool_element"
      }
    },
    {
      "weight": 5,
      "element": {
        "location": "overhauledstructures:ovds/ovds_room_part_hanging_7",
        "processors": "minecraft:empty",
        "projection": "rigid",
        "element_type": "minecraft:single_pool_element"
      }
    },
    {
      "weight": 5,
      "element": {
        "location": "overhauledstructures:ovds/ovds_room_part_hanging_8",
        "processors": "minecraft:empty",
        "projection": "rigid",
        "element_type": "minecraft:single_pool_element"
      }
    },
    {
      "weight": 5,
      "element": {
        "location": "overhauledstructures:ovds/ovds_room_part_hanging_9",
        "processors": "minecraft:empty",
        "projection": "rigid",
        "element_type": "minecraft:single_pool_element"
      }
    },
    {
      "weight": 5,
      "element": {
        "location": "overhauledstructures:ovds/ovds_room_part_hanging_10",
        "processors": "minecraft:empty",
        "projection": "rigid",
        "element_type": "minecraft:single_pool_element"
      }
    }
  ]
}